dynamodb_tools/__init__.py
dynamodb_tools/json_utils.py
dynamodb_tools-1.0.1.dist-info/LICENSE
dynamodb_tools-1.0.1.dist-info/METADATA
dynamodb_tools-1.0.1.dist-info/WHEEL
dynamodb_tools-1.0.1.dist-info/top_level.txt
dynamodb_tools-1.0.1.dist-info/RECORD
