Metadata-Version: 2.1
Name: dynamodb-tools
Version: 1.0.1
Summary: DynamoDB Tools
Home-page: https://github.com/mixja/dynamodb-tools
Author: Justin Menga
Author-email: justin.menga@gmail.com
License: ISC
Keywords: dynamodb aws tools
Platform: UNKNOWN
Classifier: Development Status :: 4 - Beta
Classifier: Intended Audience :: Developers
Classifier: Programming Language :: Python
Classifier: Programming Language :: Python :: 3
Classifier: License :: OSI Approved :: ISC License (ISCL)
Provides: dynamodb_tools
Requires-Dist: boto3
